{
    "version": "0.4",
    "template_id": 657,
    "title": "Contact",
    "type": "page",
    "metadata": {
        "template_type": "page",
        "include_in_zip": "1",
        "elementor_pro_required": null,
        "wp_page_template": "elementor_header_footer"
    },
    "content": [
        {
            "id": "a8113b3",
            "settings": {
                "flex_direction": "row",
                "flex_gap": {
                    "unit": "px",
                    "size": 0,
                    "column": "0",
                    "row": "0"
                },
                "ma_el_slider_delay": "5000",
                "padding": {
                    "unit": "px",
                    "top": "80",
                    "right": "0",
                    "bottom": "80",
                    "left": "0",
                    "isLinked": false
                },
                "flex_wrap_tablet": "wrap",
                "padding_tablet": {
                    "unit": "px",
                    "top": "40",
                    "right": "10",
                    "bottom": "40",
                    "left": "10",
                    "isLinked": false
                }
            },
            "elements": [
                {
                    "id": "8dcfa9c",
                    "settings": {
                        "flex_direction": "column",
                        "content_width": "full",
                        "width": {
                            "unit": "%",
                            "size": "50"
                        },
                        "ma_el_slider_delay": "5000",
                        "width_tablet": {
                            "unit": "%",
                            "size": 100,
                            "sizes": []
                        },
                        "width_mobile": {
                            "unit": "%",
                            "size": "",
                            "sizes": []
                        }
                    },
                    "elements": [
                        {
                            "id": "1beb695",
                            "settings": {
                                "title": "We’re here to help you on your journey.",
                                "header_size": "h1",
                                "typography_typography": "custom",
                                "typography_font_family": "Urbanist",
                                "typography_font_size": {
                                    "unit": "px",
                                    "size": 72,
                                    "sizes": []
                                },
                                "typography_font_weight": "600",
                                "typography_line_height": {
                                    "unit": "em",
                                    "size": 1.15,
                                    "sizes": []
                                },
                                "typography_letter_spacing": {
                                    "unit": "px",
                                    "size": -2,
                                    "sizes": []
                                },
                                "typography_font_size_tablet": {
                                    "unit": "px",
                                    "size": 45,
                                    "sizes": []
                                },
                                "typography_font_size_mobile": {
                                    "unit": "px",
                                    "size": 35,
                                    "sizes": []
                                },
                                "_animation": "slideInUp"
                            },
                            "widgetType": "heading",
                            "elType": "widget"
                        },
                        {
                            "id": "4050782",
                            "settings": {
                                "editor": "<p>Want to learn more about Healix, our support team is ready to help.<\/p>",
                                "typography_typography": "custom",
                                "typography_font_family": "Urbanist",
                                "typography_font_size": {
                                    "unit": "px",
                                    "size": 18,
                                    "sizes": []
                                },
                                "typography_line_height": {
                                    "unit": "em",
                                    "size": 1.5,
                                    "sizes": []
                                },
                                "text_color": "#6B6A6A",
                                "_element_width_tablet": "initial",
                                "_element_custom_width_tablet": {
                                    "unit": "px",
                                    "size": 450,
                                    "sizes": []
                                },
                                "_animation": "slideInUp"
                            },
                            "widgetType": "text-editor",
                            "elType": "widget"
                        }
                    ],
                    "elType": "container",
                    "isInner": true
                },
                {
                    "id": "a65900f",
                    "settings": {
                        "flex_direction": "column",
                        "content_width": "full",
                        "width": {
                            "unit": "%",
                            "size": "50"
                        },
                        "ma_el_slider_delay": "5000",
                        "width_tablet": {
                            "unit": "%",
                            "size": 100,
                            "sizes": []
                        },
                        "width_mobile": {
                            "unit": "%",
                            "size": "",
                            "sizes": []
                        }
                    },
                    "elements": [
                        {
                            "id": "20d4996",
                            "settings": {
                                "ma_cf7_list": "398",
                                "ma_cf7_width": {
                                    "unit": "%",
                                    "size": 100,
                                    "sizes": []
                                },
                                "ma_cf7_padding": {
                                    "unit": "px",
                                    "top": "10",
                                    "right": "10",
                                    "bottom": "10",
                                    "left": "10",
                                    "isLinked": true
                                },
                                "ma_cf7_title_typography_typography": "custom",
                                "ma_cf7_title_typography_font_family": "Urbanist",
                                "ma_cf7_title_typography_font_size": {
                                    "unit": "px",
                                    "size": 16,
                                    "sizes": []
                                },
                                "ma_cf7_title_typography_font_weight": "600",
                                "ma_cf7_field_padding": {
                                    "unit": "px",
                                    "top": "10",
                                    "right": "10",
                                    "bottom": "10",
                                    "left": "10",
                                    "isLinked": true,
                                    "size": 15
                                },
                                "ma_cf7_field_radius": {
                                    "unit": "px",
                                    "top": "15",
                                    "right": "15",
                                    "bottom": "15",
                                    "left": "15",
                                    "isLinked": true
                                },
                                "text_color_label": "#353535",
                                "ma_cf7_typography_label_typography": "custom",
                                "ma_cf7_typography_label_font_family": "Urbanist",
                                "ma_cf7_typography_label_font_size": {
                                    "unit": "px",
                                    "size": 16,
                                    "sizes": []
                                },
                                "ma_cf7_typography_label_font_weight": "600",
                                "ma_cf7_typography_label_line_height": {
                                    "unit": "em",
                                    "size": 1.6,
                                    "sizes": []
                                },
                                "ma_cf7_button_typography_typography": "custom",
                                "ma_cf7_button_typography_font_family": "Urbanist",
                                "ma_cf7_button_typography_font_size": {
                                    "unit": "px",
                                    "size": 16,
                                    "sizes": []
                                },
                                "ma_cf7_button_typography_line_height": {
                                    "unit": "em",
                                    "size": 1.6,
                                    "sizes": []
                                },
                                "ma_cf7_button_bg_color_normal_background": "classic",
                                "ma_cf7_button_bg_color_normal_color": "#000000",
                                "ma_cf7_button_border_color_normal": "#000000",
                                "ma_cf7_button_bg_color_hover_background": "classic",
                                "ma_cf7_button_bg_color_hover_color": "#2C2C2C",
                                "ma_cf7_button_text_color_hover": "#FFFFFF",
                                "ma_cf7_button_border_radius": {
                                    "unit": "px",
                                    "top": "15",
                                    "right": "15",
                                    "bottom": "15",
                                    "left": "15",
                                    "isLinked": true
                                },
                                "_border_border": "solid",
                                "_border_width": {
                                    "unit": "px",
                                    "top": "1",
                                    "right": "1",
                                    "bottom": "1",
                                    "left": "1",
                                    "isLinked": true
                                },
                                "_border_color": "#E0E0E0",
                                "_border_radius": {
                                    "unit": "px",
                                    "top": "15",
                                    "right": "15",
                                    "bottom": "15",
                                    "left": "15",
                                    "isLinked": true
                                },
                                "_animation": "fadeIn"
                            },
                            "widgetType": "ma-contact-form-7",
                            "elType": "widget"
                        }
                    ],
                    "elType": "container",
                    "isInner": true
                }
            ],
            "elType": "container",
            "isInner": false
        },
        {
            "id": "0019cbf",
            "settings": {
                "flex_direction": "row",
                "flex_gap": {
                    "unit": "px",
                    "size": 0,
                    "column": "0",
                    "row": "0"
                },
                "flex_justify_content": "space-between",
                "ma_el_slider_delay": "5000",
                "padding": {
                    "unit": "px",
                    "top": "80",
                    "right": "0",
                    "bottom": "80",
                    "left": "0",
                    "isLinked": false
                },
                "padding_tablet": {
                    "unit": "px",
                    "top": "40",
                    "right": "10",
                    "bottom": "40",
                    "left": "10",
                    "isLinked": false
                }
            },
            "elements": [
                {
                    "id": "fc3807c",
                    "settings": {
                        "flex_direction": "column",
                        "content_width": "full",
                        "width": {
                            "unit": "%",
                            "size": 38
                        },
                        "ma_el_slider_delay": "5000"
                    },
                    "elements": [
                        {
                            "id": "6329974",
                            "settings": {
                                "title": "General Inquiries",
                                "header_size": "h3",
                                "typography_typography": "custom",
                                "typography_font_family": "Urbanist",
                                "typography_font_size": {
                                    "unit": "px",
                                    "size": 36,
                                    "sizes": []
                                },
                                "typography_font_size_mobile": {
                                    "unit": "px",
                                    "size": 30,
                                    "sizes": []
                                },
                                "typography_font_weight": "600",
                                "typography_line_height": {
                                    "unit": "em",
                                    "size": 1.4,
                                    "sizes": []
                                },
                                "typography_letter_spacing": {
                                    "unit": "px",
                                    "size": -1,
                                    "sizes": []
                                },
                                "_animation": "slideInUp"
                            },
                            "widgetType": "heading",
                            "elType": "widget"
                        },
                        {
                            "id": "39985c5",
                            "settings": {
                                "editor": "<p>Interested in learning more about TaskHub? Our sales team is here to provide you with a tailored demo.<\/p>",
                                "_animation": "slideInUp"
                            },
                            "widgetType": "text-editor",
                            "elType": "widget"
                        },
                        {
                            "id": "8db5115",
                            "settings": {
                                "text": "Divider",
                                "color": "#C7C7C7",
                                "gap": {
                                    "unit": "px",
                                    "size": "",
                                    "sizes": []
                                }
                            },
                            "widgetType": "divider",
                            "elType": "widget"
                        },
                        {
                            "id": "a889556",
                            "settings": {
                                "content_width": "full",
                                "flex_gap": {
                                    "column": "0",
                                    "row": "0",
                                    "isLinked": true,
                                    "unit": "px",
                                    "size": 0
                                },
                                "ma_el_slider_delay": "5000",
                                "padding": {
                                    "unit": "px",
                                    "top": "0",
                                    "right": "0",
                                    "bottom": "0",
                                    "left": "0",
                                    "isLinked": true
                                }
                            },
                            "elements": [
                                {
                                    "id": "5108af3",
                                    "settings": {
                                        "title": "Business & Partnerships",
                                        "header_size": "div",
                                        "typography_typography": "custom",
                                        "typography_font_family": "Urbanist",
                                        "typography_font_size": {
                                            "unit": "px",
                                            "size": 16,
                                            "sizes": []
                                        },
                                        "typography_font_weight": "600",
                                        "typography_line_height": {
                                            "unit": "em",
                                            "size": 1.6,
                                            "sizes": []
                                        },
                                        "_animation": "slideInUp"
                                    },
                                    "widgetType": "heading",
                                    "elType": "widget"
                                },
                                {
                                    "id": "20d6ece",
                                    "settings": {
                                        "editor": "<p>partnerships@healix.com<\/p>",
                                        "typography_typography": "custom",
                                        "typography_font_family": "Urbanist",
                                        "typography_font_size": {
                                            "unit": "px",
                                            "size": 14,
                                            "sizes": []
                                        },
                                        "typography_line_height": {
                                            "unit": "em",
                                            "size": 1.6,
                                            "sizes": []
                                        },
                                        "_animation": "slideInUp"
                                    },
                                    "widgetType": "text-editor",
                                    "elType": "widget"
                                }
                            ],
                            "elType": "container",
                            "isInner": true
                        },
                        {
                            "id": "675c7ce",
                            "settings": {
                                "content_width": "full",
                                "flex_gap": {
                                    "column": "0",
                                    "row": "0",
                                    "isLinked": true,
                                    "unit": "px",
                                    "size": 0
                                },
                                "ma_el_slider_delay": "5000",
                                "padding": {
                                    "unit": "px",
                                    "top": "0",
                                    "right": "0",
                                    "bottom": "0",
                                    "left": "0",
                                    "isLinked": true
                                }
                            },
                            "elements": [
                                {
                                    "id": "561fe1d",
                                    "settings": {
                                        "title": "Press & Media",
                                        "header_size": "div",
                                        "typography_typography": "custom",
                                        "typography_font_family": "Urbanist",
                                        "typography_font_size": {
                                            "unit": "px",
                                            "size": 16,
                                            "sizes": []
                                        },
                                        "typography_font_weight": "600",
                                        "typography_line_height": {
                                            "unit": "em",
                                            "size": 1.6,
                                            "sizes": []
                                        },
                                        "_animation": "slideInUp"
                                    },
                                    "widgetType": "heading",
                                    "elType": "widget"
                                },
                                {
                                    "id": "e5e97fd",
                                    "settings": {
                                        "editor": "<p>media@healix.com<\/p>",
                                        "typography_typography": "custom",
                                        "typography_font_family": "Urbanist",
                                        "typography_font_size": {
                                            "unit": "px",
                                            "size": 14,
                                            "sizes": []
                                        },
                                        "typography_line_height": {
                                            "unit": "em",
                                            "size": 1.6,
                                            "sizes": []
                                        },
                                        "_animation": "slideInUp"
                                    },
                                    "widgetType": "text-editor",
                                    "elType": "widget"
                                }
                            ],
                            "elType": "container",
                            "isInner": true
                        }
                    ],
                    "elType": "container",
                    "isInner": true
                },
                {
                    "id": "c5e2f82",
                    "settings": {
                        "flex_direction": "column",
                        "content_width": "full",
                        "width": {
                            "unit": "%",
                            "size": 38
                        },
                        "ma_el_slider_delay": "5000"
                    },
                    "elements": [
                        {
                            "id": "f757a3d",
                            "settings": {
                                "title": "Customer Support",
                                "header_size": "h3",
                                "typography_typography": "custom",
                                "typography_font_family": "Urbanist",
                                "typography_font_size": {
                                    "unit": "px",
                                    "size": 36,
                                    "sizes": []
                                },
                                "typography_font_size_mobile": {
                                    "unit": "px",
                                    "size": 30,
                                    "sizes": []
                                },
                                "typography_font_weight": "600",
                                "typography_line_height": {
                                    "unit": "em",
                                    "size": 1.4,
                                    "sizes": []
                                },
                                "typography_letter_spacing": {
                                    "unit": "px",
                                    "size": -1,
                                    "sizes": []
                                },
                                "_animation": "slideInUp",
                                "animation_duration": "slow"
                            },
                            "widgetType": "heading",
                            "elType": "widget"
                        },
                        {
                            "id": "66a6dd9",
                            "settings": {
                                "editor": "<p>We’re here to help! Whether you have a question about TaskHub’s features, need assistance.<\/p>",
                                "_animation": "slideInUp",
                                "animation_duration": "slow"
                            },
                            "widgetType": "text-editor",
                            "elType": "widget"
                        },
                        {
                            "id": "ea459ce",
                            "settings": {
                                "text": "Divider",
                                "color": "#C7C7C7",
                                "gap": {
                                    "unit": "px",
                                    "size": "",
                                    "sizes": []
                                }
                            },
                            "widgetType": "divider",
                            "elType": "widget"
                        },
                        {
                            "id": "23bd505",
                            "settings": {
                                "content_width": "full",
                                "flex_gap": {
                                    "column": "0",
                                    "row": "0",
                                    "isLinked": true,
                                    "unit": "px",
                                    "size": 0
                                },
                                "ma_el_slider_delay": "5000",
                                "padding": {
                                    "unit": "px",
                                    "top": "0",
                                    "right": "0",
                                    "bottom": "0",
                                    "left": "0",
                                    "isLinked": true
                                }
                            },
                            "elements": [
                                {
                                    "id": "77f2a61",
                                    "settings": {
                                        "title": "Customer Support Email",
                                        "header_size": "div",
                                        "typography_typography": "custom",
                                        "typography_font_family": "Urbanist",
                                        "typography_font_size": {
                                            "unit": "px",
                                            "size": 16,
                                            "sizes": []
                                        },
                                        "typography_font_weight": "600",
                                        "typography_line_height": {
                                            "unit": "em",
                                            "size": 1.6,
                                            "sizes": []
                                        },
                                        "_animation": "slideInUp",
                                        "animation_duration": "slow"
                                    },
                                    "widgetType": "heading",
                                    "elType": "widget"
                                },
                                {
                                    "id": "cfb003e",
                                    "settings": {
                                        "editor": "<p>support@healix.com<\/p>",
                                        "typography_typography": "custom",
                                        "typography_font_family": "Urbanist",
                                        "typography_font_size": {
                                            "unit": "px",
                                            "size": 14,
                                            "sizes": []
                                        },
                                        "typography_line_height": {
                                            "unit": "em",
                                            "size": 1.6,
                                            "sizes": []
                                        },
                                        "_animation": "slideInUp",
                                        "animation_duration": "slow"
                                    },
                                    "widgetType": "text-editor",
                                    "elType": "widget"
                                }
                            ],
                            "elType": "container",
                            "isInner": true
                        },
                        {
                            "id": "c031393",
                            "settings": {
                                "content_width": "full",
                                "flex_gap": {
                                    "column": "0",
                                    "row": "0",
                                    "isLinked": true,
                                    "unit": "px",
                                    "size": 0
                                },
                                "ma_el_slider_delay": "5000",
                                "padding": {
                                    "unit": "px",
                                    "top": "0",
                                    "right": "0",
                                    "bottom": "0",
                                    "left": "0",
                                    "isLinked": true
                                }
                            },
                            "elements": [
                                {
                                    "id": "92588db",
                                    "settings": {
                                        "title": "Phone Support",
                                        "header_size": "div",
                                        "typography_typography": "custom",
                                        "typography_font_family": "Urbanist",
                                        "typography_font_size": {
                                            "unit": "px",
                                            "size": 16,
                                            "sizes": []
                                        },
                                        "typography_font_weight": "600",
                                        "typography_line_height": {
                                            "unit": "em",
                                            "size": 1.6,
                                            "sizes": []
                                        },
                                        "_animation": "slideInUp",
                                        "animation_duration": "slow"
                                    },
                                    "widgetType": "heading",
                                    "elType": "widget"
                                },
                                {
                                    "id": "4cd01b0",
                                    "settings": {
                                        "editor": "<p>+1 (800) 123-4567<\/p>",
                                        "typography_typography": "custom",
                                        "typography_font_family": "Urbanist",
                                        "typography_font_size": {
                                            "unit": "px",
                                            "size": 14,
                                            "sizes": []
                                        },
                                        "typography_line_height": {
                                            "unit": "em",
                                            "size": 1.6,
                                            "sizes": []
                                        },
                                        "_animation": "slideInUp",
                                        "animation_duration": "slow"
                                    },
                                    "widgetType": "text-editor",
                                    "elType": "widget"
                                }
                            ],
                            "elType": "container",
                            "isInner": true
                        }
                    ],
                    "elType": "container",
                    "isInner": true
                }
            ],
            "elType": "container",
            "isInner": false
        },
        {
            "id": "3ad56d4",
            "settings": {
                "flex_direction": "column",
                "ma_el_slider_delay": "5000",
                "padding": {
                    "unit": "px",
                    "top": "80",
                    "right": "0",
                    "bottom": "80",
                    "left": "0",
                    "isLinked": false
                },
                "padding_tablet": {
                    "unit": "px",
                    "top": "40",
                    "right": "10",
                    "bottom": "40",
                    "left": "10",
                    "isLinked": false
                }
            },
            "elements": [
                {
                    "id": "6651fb2",
                    "settings": {
                        "content_width": "full",
                        "flex_direction": "row",
                        "background_background": "classic",
                        "background_color": "#F0F5F6",
                        "ma_el_slider_delay": "5000",
                        "border_radius": {
                            "unit": "px",
                            "top": "15",
                            "right": "15",
                            "bottom": "15",
                            "left": "15",
                            "isLinked": true
                        },
                        "padding": {
                            "unit": "px",
                            "top": "40",
                            "right": "40",
                            "bottom": "40",
                            "left": "40",
                            "isLinked": true
                        },
                        "padding_mobile": {
                            "unit": "px",
                            "top": "15",
                            "right": "15",
                            "bottom": "15",
                            "left": "15",
                            "isLinked": true
                        }
                    },
                    "elements": [
                        {
                            "id": "d19222d",
                            "settings": {
                                "content_width": "full",
                                "ma_el_slider_delay": "5000"
                            },
                            "elements": [
                                {
                                    "id": "df517f0",
                                    "settings": {
                                        "title": "Frequently\nasked questions",
                                        "typography_typography": "custom",
                                        "typography_font_family": "Urbanist",
                                        "typography_font_size": {
                                            "unit": "px",
                                            "size": 54,
                                            "sizes": []
                                        },
                                        "typography_font_size_tablet": {
                                            "unit": "px",
                                            "size": 35,
                                            "sizes": []
                                        },
                                        "typography_font_size_mobile": {
                                            "unit": "px",
                                            "size": 30,
                                            "sizes": []
                                        },
                                        "typography_font_weight": "600",
                                        "typography_line_height": {
                                            "unit": "em",
                                            "size": 1.2,
                                            "sizes": []
                                        },
                                        "typography_letter_spacing": {
                                            "unit": "px",
                                            "size": -1,
                                            "sizes": []
                                        },
                                        "_animation": "slideInUp"
                                    },
                                    "widgetType": "heading",
                                    "elType": "widget"
                                },
                                {
                                    "id": "3a74e49",
                                    "settings": {
                                        "editor": "<p>For any unanswered questions, reach out to our support team via email. We'll respond as soon as possible to assist you.<\/p>",
                                        "typography_typography": "custom",
                                        "typography_font_family": "Urbanist",
                                        "typography_font_size": {
                                            "unit": "px",
                                            "size": 18,
                                            "sizes": []
                                        },
                                        "typography_font_size_mobile": {
                                            "unit": "px",
                                            "size": 16,
                                            "sizes": []
                                        },
                                        "typography_line_height": {
                                            "unit": "em",
                                            "size": 1.6,
                                            "sizes": []
                                        },
                                        "_animation": "slideInUp"
                                    },
                                    "widgetType": "text-editor",
                                    "elType": "widget"
                                }
                            ],
                            "elType": "container",
                            "isInner": true
                        },
                        {
                            "id": "7fc4bbc",
                            "settings": {
                                "content_width": "full",
                                "ma_el_slider_delay": "5000"
                            },
                            "elements": [
                                {
                                    "id": "878fe37",
                                    "settings": {
                                        "items": [
                                            {
                                                "item_title": "How secure is my data with Healix?",
                                                "_id": "a93f0b1"
                                            },
                                            {
                                                "item_title": "Can I use Healix without any wearable devices?",
                                                "_id": "08c3a37"
                                            },
                                            {
                                                "item_title": "What’s included in the doctor chat support?",
                                                "_id": "11c3d8a"
                                            },
                                            {
                                                "_id": "88859d4",
                                                "item_title": "Can I upgrade or downgrade my plan later?"
                                            },
                                            {
                                                "_id": "bff889f",
                                                "item_title": "Does Healix offer a free trial?"
                                            }
                                        ],
                                        "accordion_item_title_position_horizontal": "stretch",
                                        "accordion_item_title_icon_position": "end",
                                        "accordion_item_title_space_between": {
                                            "unit": "px",
                                            "size": 21,
                                            "sizes": []
                                        },
                                        "accordion_border_normal_border": "none",
                                        "title_typography_typography": "custom",
                                        "title_typography_font_family": "Urbanist",
                                        "title_typography_font_size": {
                                            "unit": "px",
                                            "size": 17,
                                            "sizes": []
                                        },
                                        "title_typography_font_size_tablet": {
                                            "unit": "px",
                                            "size": 16,
                                            "sizes": []
                                        },
                                        "title_typography_font_weight": "600",
                                        "title_typography_line_height": {
                                            "unit": "em",
                                            "size": 1.7,
                                            "sizes": []
                                        },
                                        "content_border_border": "none",
                                        "_animation": "fadeIn"
                                    },
                                    "elements": [
                                        {
                                            "id": "18f315b",
                                            "settings": {
                                                "_title": "item #1",
                                                "content_width": "full",
                                                "ma_el_slider_delay": "5000"
                                            },
                                            "elements": [
                                                {
                                                    "id": "d6fd928",
                                                    "settings": {
                                                        "editor": "<p>Your privacy is our top priority. Healix uses advanced encryption to protect your data, and you have full control over.<\/p>",
                                                        "typography_typography": "custom",
                                                        "typography_font_family": "Urbanist",
                                                        "typography_font_size": {
                                                            "unit": "px",
                                                            "size": 16,
                                                            "sizes": []
                                                        },
                                                        "typography_line_height": {
                                                            "unit": "em",
                                                            "size": 1.6,
                                                            "sizes": []
                                                        }
                                                    },
                                                    "widgetType": "text-editor",
                                                    "elType": "widget"
                                                }
                                            ],
                                            "elType": "container",
                                            "isInner": true
                                        },
                                        {
                                            "id": "618d705",
                                            "settings": {
                                                "_title": "item #2",
                                                "content_width": "full",
                                                "ma_el_slider_delay": "5000"
                                            },
                                            "elements": [
                                                {
                                                    "id": "31a1a03",
                                                    "settings": {
                                                        "editor": "<p>Your privacy is our top priority. Healix uses advanced encryption to protect your data, and you have full control over.<\/p>",
                                                        "typography_typography": "custom",
                                                        "typography_font_family": "Urbanist",
                                                        "typography_font_size": {
                                                            "unit": "px",
                                                            "size": 16,
                                                            "sizes": []
                                                        },
                                                        "typography_line_height": {
                                                            "unit": "em",
                                                            "size": 1.6,
                                                            "sizes": []
                                                        }
                                                    },
                                                    "widgetType": "text-editor",
                                                    "elType": "widget"
                                                }
                                            ],
                                            "elType": "container",
                                            "isInner": true
                                        },
                                        {
                                            "id": "a4c3ed9",
                                            "settings": {
                                                "_title": "item #3",
                                                "content_width": "full",
                                                "ma_el_slider_delay": "5000"
                                            },
                                            "elements": [
                                                {
                                                    "id": "8c9ff85",
                                                    "settings": {
                                                        "editor": "<p>Your privacy is our top priority. Healix uses advanced encryption to protect your data, and you have full control over.<\/p>",
                                                        "typography_typography": "custom",
                                                        "typography_font_family": "Urbanist",
                                                        "typography_font_size": {
                                                            "unit": "px",
                                                            "size": 16,
                                                            "sizes": []
                                                        },
                                                        "typography_line_height": {
                                                            "unit": "em",
                                                            "size": 1.6,
                                                            "sizes": []
                                                        }
                                                    },
                                                    "widgetType": "text-editor",
                                                    "elType": "widget"
                                                }
                                            ],
                                            "elType": "container",
                                            "isInner": true
                                        },
                                        {
                                            "id": "fe3c542",
                                            "settings": {
                                                "_title": "Item #4",
                                                "ma_el_slider_delay": "5000"
                                            },
                                            "elements": [
                                                {
                                                    "id": "e53d832",
                                                    "settings": {
                                                        "editor": "<p>Your privacy is our top priority. Healix uses advanced encryption to protect your data, and you have full control over.<\/p>",
                                                        "typography_typography": "custom",
                                                        "typography_font_family": "Urbanist",
                                                        "typography_font_size": {
                                                            "unit": "px",
                                                            "size": 16,
                                                            "sizes": []
                                                        },
                                                        "typography_line_height": {
                                                            "unit": "em",
                                                            "size": 1.6,
                                                            "sizes": []
                                                        }
                                                    },
                                                    "widgetType": "text-editor",
                                                    "elType": "widget"
                                                }
                                            ],
                                            "elType": "container",
                                            "isInner": true
                                        },
                                        {
                                            "id": "67d054f",
                                            "settings": {
                                                "_title": "Item #5",
                                                "ma_el_slider_delay": "5000"
                                            },
                                            "elements": [
                                                {
                                                    "id": "dc34cca",
                                                    "settings": {
                                                        "editor": "<p>Your privacy is our top priority. Healix uses advanced encryption to protect your data, and you have full control over.<\/p>",
                                                        "typography_typography": "custom",
                                                        "typography_font_family": "Urbanist",
                                                        "typography_font_size": {
                                                            "unit": "px",
                                                            "size": 16,
                                                            "sizes": []
                                                        },
                                                        "typography_line_height": {
                                                            "unit": "em",
                                                            "size": 1.6,
                                                            "sizes": []
                                                        }
                                                    },
                                                    "widgetType": "text-editor",
                                                    "elType": "widget"
                                                }
                                            ],
                                            "elType": "container",
                                            "isInner": true
                                        }
                                    ],
                                    "widgetType": "nested-accordion",
                                    "elType": "widget"
                                }
                            ],
                            "elType": "container",
                            "isInner": true
                        }
                    ],
                    "elType": "container",
                    "isInner": true
                }
            ],
            "elType": "container",
            "isInner": false
        }
    ]
}