{
    "version": "0.4",
    "template_id": 518,
    "title": "Refund Policy",
    "type": "page",
    "metadata": {
        "template_type": "page",
        "include_in_zip": "1",
        "elementor_pro_required": null,
        "wp_page_template": "elementor_header_footer"
    },
    "content": [
        {
            "id": "42ae2314",
            "settings": {
                "content_width": "full",
                "flex_gap": {
                    "column": "0",
                    "row": "0",
                    "isLinked": false,
                    "unit": "px",
                    "size": 0
                },
                "background_background": "classic",
                "background_color": "#000000",
                "ma_el_slider_delay": "5000",
                "padding": {
                    "unit": "px",
                    "top": "87",
                    "right": "20",
                    "bottom": "80",
                    "left": "20",
                    "isLinked": false
                }
            },
            "elements": [
                {
                    "id": "6b09eeb3",
                    "settings": {
                        "boxed_width": {
                            "unit": "px",
                            "size": 1295,
                            "sizes": []
                        },
                        "flex_gap": {
                            "column": "0",
                            "row": "0",
                            "isLinked": false,
                            "unit": "px",
                            "size": 0
                        },
                        "ma_el_slider_delay": "5000",
                        "padding": {
                            "unit": "px",
                            "top": "0",
                            "right": "0",
                            "bottom": "0",
                            "left": "0",
                            "isLinked": false
                        }
                    },
                    "elements": [
                        {
                            "id": "4d31345",
                            "settings": {
                                "title": "Refund Policy",
                                "align": "center",
                                "typography_typography": "custom",
                                "typography_font_family": "Inter",
                                "typography_font_size": {
                                    "unit": "px",
                                    "size": 90,
                                    "sizes": []
                                },
                                "typography_font_size_tablet": {
                                    "unit": "px",
                                    "size": 60,
                                    "sizes": []
                                },
                                "typography_font_size_mobile": {
                                    "unit": "px",
                                    "size": 48,
                                    "sizes": []
                                },
                                "typography_font_weight": "600",
                                "typography_line_height": {
                                    "unit": "custom",
                                    "size": "110%",
                                    "sizes": []
                                },
                                "typography_line_height_tablet": {
                                    "unit": "custom",
                                    "size": "",
                                    "sizes": []
                                },
                                "typography_line_height_mobile": {
                                    "unit": "custom",
                                    "size": "",
                                    "sizes": []
                                },
                                "typography_letter_spacing": {
                                    "unit": "px",
                                    "size": -3,
                                    "sizes": []
                                },
                                "title_color": "#FFFFFF",
                                "header_size": "h1"
                            },
                            "widgetType": "heading",
                            "elType": "widget"
                        },
                        {
                            "id": "5583316f",
                            "settings": {
                                "title": "Thank you for choosing Termix. We want you to be satisfied with our service. This Refund Policy outlines when and how refunds may be issued.",
                                "header_size": "p",
                                "align": "center",
                                "typography_typography": "custom",
                                "typography_font_family": "Inter",
                                "typography_font_size": {
                                    "unit": "px",
                                    "size": 18,
                                    "sizes": []
                                },
                                "typography_font_weight": "400",
                                "typography_line_height": {
                                    "unit": "px",
                                    "size": 28,
                                    "sizes": []
                                },
                                "title_color": "#BABBC3",
                                "_margin": {
                                    "unit": "px",
                                    "top": "24",
                                    "right": "0",
                                    "bottom": "0",
                                    "left": "0",
                                    "isLinked": false
                                },
                                "_element_width": "initial",
                                "_element_custom_width": {
                                    "unit": "px",
                                    "size": 803,
                                    "sizes": []
                                },
                                "_flex_align_self": "center"
                            },
                            "widgetType": "heading",
                            "elType": "widget"
                        }
                    ],
                    "elType": "container",
                    "isInner": true
                }
            ],
            "elType": "container",
            "isInner": false
        },
        {
            "id": "2769c08d",
            "settings": {
                "flex_direction": "column",
                "content_width": "full",
                "flex_gap": {
                    "column": "0",
                    "row": "0",
                    "isLinked": false,
                    "unit": "px",
                    "size": 0
                },
                "background_background": "classic",
                "background_color": "#000000",
                "ma_el_slider_delay": "5000",
                "padding": {
                    "unit": "px",
                    "top": "0",
                    "right": "20",
                    "bottom": "80",
                    "left": "20",
                    "isLinked": false
                }
            },
            "elements": [
                {
                    "id": "cb5521c",
                    "settings": {
                        "content_width": "full",
                        "width": {
                            "unit": "px",
                            "size": 1043,
                            "sizes": []
                        },
                        "width_tablet": {
                            "unit": "%",
                            "size": 100,
                            "sizes": []
                        },
                        "width_mobile": {
                            "unit": "%",
                            "size": "",
                            "sizes": []
                        },
                        "flex_gap": {
                            "column": "0",
                            "row": "40",
                            "isLinked": false,
                            "unit": "px",
                            "size": 0
                        },
                        "ma_el_slider_delay": "5000",
                        "margin": {
                            "unit": "px",
                            "top": "0",
                            "right": "0",
                            "bottom": "0",
                            "left": "0",
                            "isLinked": false
                        },
                        "margin_tablet": {
                            "unit": "px",
                            "top": "40",
                            "right": "0",
                            "bottom": "0",
                            "left": "0",
                            "isLinked": false
                        },
                        "padding": {
                            "unit": "px",
                            "top": "0",
                            "right": "0",
                            "bottom": "0",
                            "left": "0",
                            "isLinked": false
                        },
                        "_flex_align_self": "center"
                    },
                    "elements": [
                        {
                            "id": "54c83649",
                            "settings": {
                                "content_width": "full",
                                "flex_gap": {
                                    "column": "0",
                                    "row": "20",
                                    "isLinked": false,
                                    "unit": "px",
                                    "size": 0
                                },
                                "flex_gap_tablet": {
                                    "column": "",
                                    "row": "",
                                    "isLinked": true,
                                    "unit": "px",
                                    "size": null
                                },
                                "ma_el_slider_delay": "5000",
                                "padding": {
                                    "unit": "px",
                                    "top": "0",
                                    "right": "0",
                                    "bottom": "0",
                                    "left": "0",
                                    "isLinked": false
                                }
                            },
                            "elements": [
                                {
                                    "id": "326f8577",
                                    "settings": {
                                        "title": "1. Subscription Payments",
                                        "header_size": "h4",
                                        "typography_typography": "custom",
                                        "typography_font_family": "Inter",
                                        "typography_font_size": {
                                            "unit": "px",
                                            "size": 24,
                                            "sizes": []
                                        },
                                        "typography_font_weight": "600",
                                        "typography_line_height": {
                                            "unit": "px",
                                            "size": 36,
                                            "sizes": []
                                        },
                                        "title_color": "#EFF1F2"
                                    },
                                    "widgetType": "heading",
                                    "elType": "widget"
                                },
                                {
                                    "id": "51ae2b29",
                                    "settings": {
                                        "editor": "<p>All Termix subscriptions are billed in advance on a recurring basis (monthly or yearly), depending on the plan you choose.<\/p>",
                                        "typography_typography": "custom",
                                        "typography_font_family": "Inter",
                                        "typography_font_size": {
                                            "unit": "px",
                                            "size": 16,
                                            "sizes": []
                                        },
                                        "typography_font_weight": "400",
                                        "typography_line_height": {
                                            "unit": "px",
                                            "size": 26,
                                            "sizes": []
                                        },
                                        "text_color": "#BABBC3"
                                    },
                                    "widgetType": "text-editor",
                                    "elType": "widget"
                                }
                            ],
                            "elType": "container",
                            "isInner": true
                        },
                        {
                            "id": "2da7454c",
                            "settings": {
                                "content_width": "full",
                                "flex_gap": {
                                    "column": "0",
                                    "row": "20",
                                    "isLinked": false,
                                    "unit": "px",
                                    "size": 0
                                },
                                "flex_gap_tablet": {
                                    "column": "",
                                    "row": "",
                                    "isLinked": true,
                                    "unit": "px",
                                    "size": null
                                },
                                "ma_el_slider_delay": "5000",
                                "padding": {
                                    "unit": "px",
                                    "top": "0",
                                    "right": "0",
                                    "bottom": "0",
                                    "left": "0",
                                    "isLinked": false
                                }
                            },
                            "elements": [
                                {
                                    "id": "188dce45",
                                    "settings": {
                                        "title": "2. Free Trial (If Applicable)",
                                        "header_size": "h4",
                                        "typography_typography": "custom",
                                        "typography_font_family": "Inter",
                                        "typography_font_size": {
                                            "unit": "px",
                                            "size": 24,
                                            "sizes": []
                                        },
                                        "typography_font_weight": "600",
                                        "typography_line_height": {
                                            "unit": "px",
                                            "size": 36,
                                            "sizes": []
                                        },
                                        "title_color": "#EFF1F2"
                                    },
                                    "widgetType": "heading",
                                    "elType": "widget"
                                },
                                {
                                    "id": "6f5cda6f",
                                    "settings": {
                                        "editor": "<p>If your plan includes a free trial, we encourage you to evaluate Termix during this period. Once the trial ends and payment is processed, the subscription becomes active and non-refundable.<\/p>",
                                        "typography_typography": "custom",
                                        "typography_font_family": "Inter",
                                        "typography_font_size": {
                                            "unit": "px",
                                            "size": 16,
                                            "sizes": []
                                        },
                                        "typography_font_weight": "400",
                                        "typography_line_height": {
                                            "unit": "px",
                                            "size": 26,
                                            "sizes": []
                                        },
                                        "text_color": "#BABBC3"
                                    },
                                    "widgetType": "text-editor",
                                    "elType": "widget"
                                }
                            ],
                            "elType": "container",
                            "isInner": true
                        },
                        {
                            "id": "3c90f9df",
                            "settings": {
                                "content_width": "full",
                                "flex_gap": {
                                    "column": "0",
                                    "row": "20",
                                    "isLinked": false,
                                    "unit": "px",
                                    "size": 0
                                },
                                "flex_gap_tablet": {
                                    "column": "",
                                    "row": "",
                                    "isLinked": true,
                                    "unit": "px",
                                    "size": null
                                },
                                "ma_el_slider_delay": "5000",
                                "padding": {
                                    "unit": "px",
                                    "top": "0",
                                    "right": "0",
                                    "bottom": "0",
                                    "left": "0",
                                    "isLinked": false
                                }
                            },
                            "elements": [
                                {
                                    "id": "1059529d",
                                    "settings": {
                                        "title": "3. Refund Eligibility",
                                        "header_size": "h4",
                                        "typography_typography": "custom",
                                        "typography_font_family": "Inter",
                                        "typography_font_size": {
                                            "unit": "px",
                                            "size": 24,
                                            "sizes": []
                                        },
                                        "typography_font_weight": "600",
                                        "typography_line_height": {
                                            "unit": "px",
                                            "size": 36,
                                            "sizes": []
                                        },
                                        "title_color": "#EFF1F2"
                                    },
                                    "widgetType": "heading",
                                    "elType": "widget"
                                },
                                {
                                    "id": "36b250e",
                                    "settings": {
                                        "editor": "<p>Refunds may be issued under the following conditions:<\/p><ul data-spread=\"false\"><li>You request a refund within <strong>7 days<\/strong> of your initial subscription purchase<\/li><li>The request applies only to <strong>first-time subscriptions<\/strong><\/li><\/ul><p>Renewal payments are <strong>non-refundable<\/strong>.<\/p>",
                                        "typography_typography": "custom",
                                        "typography_font_family": "Inter",
                                        "typography_font_size": {
                                            "unit": "px",
                                            "size": 16,
                                            "sizes": []
                                        },
                                        "typography_font_weight": "400",
                                        "typography_line_height": {
                                            "unit": "px",
                                            "size": 26,
                                            "sizes": []
                                        },
                                        "text_color": "#BABBC3"
                                    },
                                    "widgetType": "text-editor",
                                    "elType": "widget"
                                }
                            ],
                            "elType": "container",
                            "isInner": true
                        },
                        {
                            "id": "5a35c4bd",
                            "settings": {
                                "content_width": "full",
                                "flex_gap": {
                                    "column": "0",
                                    "row": "20",
                                    "isLinked": false,
                                    "unit": "px",
                                    "size": 0
                                },
                                "flex_gap_tablet": {
                                    "column": "",
                                    "row": "",
                                    "isLinked": true,
                                    "unit": "px",
                                    "size": null
                                },
                                "ma_el_slider_delay": "5000",
                                "padding": {
                                    "unit": "px",
                                    "top": "0",
                                    "right": "0",
                                    "bottom": "0",
                                    "left": "0",
                                    "isLinked": false
                                }
                            },
                            "elements": [
                                {
                                    "id": "7a700581",
                                    "settings": {
                                        "title": "4. Non-Refundable Cases",
                                        "header_size": "h4",
                                        "typography_typography": "custom",
                                        "typography_font_family": "Inter",
                                        "typography_font_size": {
                                            "unit": "px",
                                            "size": 24,
                                            "sizes": []
                                        },
                                        "typography_font_weight": "600",
                                        "typography_line_height": {
                                            "unit": "px",
                                            "size": 36,
                                            "sizes": []
                                        },
                                        "title_color": "#EFF1F2"
                                    },
                                    "widgetType": "heading",
                                    "elType": "widget"
                                },
                                {
                                    "id": "27940601",
                                    "settings": {
                                        "editor": "<p>Refunds will <strong>not<\/strong> be provided for:<\/p><ul data-spread=\"false\"><li>Partial use of the service<\/li><li>Failure to cancel before the renewal date<\/li><li>Account suspension or termination due to Terms &amp; Conditions violations<\/li><li>Promotional or discounted plans (unless required by law)<\/li><\/ul>",
                                        "typography_typography": "custom",
                                        "typography_font_family": "Inter",
                                        "typography_font_size": {
                                            "unit": "px",
                                            "size": 16,
                                            "sizes": []
                                        },
                                        "typography_font_weight": "400",
                                        "typography_line_height": {
                                            "unit": "px",
                                            "size": 26,
                                            "sizes": []
                                        },
                                        "text_color": "#BABBC3"
                                    },
                                    "widgetType": "text-editor",
                                    "elType": "widget"
                                }
                            ],
                            "elType": "container",
                            "isInner": true
                        },
                        {
                            "id": "5e05c0e0",
                            "settings": {
                                "content_width": "full",
                                "flex_gap": {
                                    "column": "0",
                                    "row": "20",
                                    "isLinked": false,
                                    "unit": "px",
                                    "size": 0
                                },
                                "flex_gap_tablet": {
                                    "column": "",
                                    "row": "",
                                    "isLinked": true,
                                    "unit": "px",
                                    "size": null
                                },
                                "ma_el_slider_delay": "5000",
                                "padding": {
                                    "unit": "px",
                                    "top": "0",
                                    "right": "0",
                                    "bottom": "0",
                                    "left": "0",
                                    "isLinked": false
                                }
                            },
                            "elements": [
                                {
                                    "id": "2d309cc1",
                                    "settings": {
                                        "title": "5. How to Request a Refund",
                                        "header_size": "h4",
                                        "typography_typography": "custom",
                                        "typography_font_family": "Inter",
                                        "typography_font_size": {
                                            "unit": "px",
                                            "size": 24,
                                            "sizes": []
                                        },
                                        "typography_font_weight": "600",
                                        "typography_line_height": {
                                            "unit": "px",
                                            "size": 36,
                                            "sizes": []
                                        },
                                        "title_color": "#EFF1F2"
                                    },
                                    "widgetType": "heading",
                                    "elType": "widget"
                                },
                                {
                                    "id": "14ab4c7b",
                                    "settings": {
                                        "editor": "<p>To request a refund, please contact us at <a href=\"#\">test@finix.com<\/a> with:<\/p><ul data-spread=\"false\"><li>Your registered email address<\/li><li>Subscription plan details<\/li><li>Reason for the refund request<\/li><\/ul>",
                                        "typography_typography": "custom",
                                        "typography_font_family": "Inter",
                                        "typography_font_size": {
                                            "unit": "px",
                                            "size": 16,
                                            "sizes": []
                                        },
                                        "typography_font_weight": "400",
                                        "typography_line_height": {
                                            "unit": "px",
                                            "size": 26,
                                            "sizes": []
                                        },
                                        "text_color": "#BABBC3",
                                        "link_color": "#7AB7FF"
                                    },
                                    "widgetType": "text-editor",
                                    "elType": "widget"
                                }
                            ],
                            "elType": "container",
                            "isInner": true
                        },
                        {
                            "id": "8967d9f",
                            "settings": {
                                "content_width": "full",
                                "flex_gap": {
                                    "column": "0",
                                    "row": "20",
                                    "isLinked": false,
                                    "unit": "px",
                                    "size": 0
                                },
                                "flex_gap_tablet": {
                                    "column": "",
                                    "row": "",
                                    "isLinked": true,
                                    "unit": "px",
                                    "size": null
                                },
                                "ma_el_slider_delay": "5000",
                                "padding": {
                                    "unit": "px",
                                    "top": "0",
                                    "right": "0",
                                    "bottom": "0",
                                    "left": "0",
                                    "isLinked": false
                                }
                            },
                            "elements": [
                                {
                                    "id": "7dd4e41",
                                    "settings": {
                                        "title": "6. Refund Processing",
                                        "header_size": "h4",
                                        "typography_typography": "custom",
                                        "typography_font_family": "Inter",
                                        "typography_font_size": {
                                            "unit": "px",
                                            "size": 24,
                                            "sizes": []
                                        },
                                        "typography_font_weight": "600",
                                        "typography_line_height": {
                                            "unit": "px",
                                            "size": 36,
                                            "sizes": []
                                        },
                                        "title_color": "#EFF1F2"
                                    },
                                    "widgetType": "heading",
                                    "elType": "widget"
                                },
                                {
                                    "id": "7e53f7ce",
                                    "settings": {
                                        "editor": "<p>Approved refunds will be processed within <strong>5–10 business days<\/strong> and credited back to the original payment method.<\/p>",
                                        "typography_typography": "custom",
                                        "typography_font_family": "Inter",
                                        "typography_font_size": {
                                            "unit": "px",
                                            "size": 16,
                                            "sizes": []
                                        },
                                        "typography_font_weight": "400",
                                        "typography_line_height": {
                                            "unit": "px",
                                            "size": 26,
                                            "sizes": []
                                        },
                                        "text_color": "#BABBC3"
                                    },
                                    "widgetType": "text-editor",
                                    "elType": "widget"
                                }
                            ],
                            "elType": "container",
                            "isInner": true
                        },
                        {
                            "id": "5c9ad226",
                            "settings": {
                                "content_width": "full",
                                "flex_gap": {
                                    "column": "0",
                                    "row": "20",
                                    "isLinked": false,
                                    "unit": "px",
                                    "size": 0
                                },
                                "flex_gap_tablet": {
                                    "column": "",
                                    "row": "",
                                    "isLinked": true,
                                    "unit": "px",
                                    "size": null
                                },
                                "ma_el_slider_delay": "5000",
                                "padding": {
                                    "unit": "px",
                                    "top": "0",
                                    "right": "0",
                                    "bottom": "0",
                                    "left": "0",
                                    "isLinked": false
                                }
                            },
                            "elements": [
                                {
                                    "id": "54bcee31",
                                    "settings": {
                                        "title": "7. Policy Updates",
                                        "header_size": "h4",
                                        "typography_typography": "custom",
                                        "typography_font_family": "Inter",
                                        "typography_font_size": {
                                            "unit": "px",
                                            "size": 24,
                                            "sizes": []
                                        },
                                        "typography_font_weight": "600",
                                        "typography_line_height": {
                                            "unit": "px",
                                            "size": 36,
                                            "sizes": []
                                        },
                                        "title_color": "#EFF1F2"
                                    },
                                    "widgetType": "heading",
                                    "elType": "widget"
                                },
                                {
                                    "id": "67848f1a",
                                    "settings": {
                                        "editor": "<p>We reserve the right to modify this Refund Policy at any time. Changes will take effect immediately upon posting on our website.<\/p><p>If you have any questions regarding refunds, feel free to reach out to our support team.<\/p>",
                                        "typography_typography": "custom",
                                        "typography_font_family": "Inter",
                                        "typography_font_size": {
                                            "unit": "px",
                                            "size": 16,
                                            "sizes": []
                                        },
                                        "typography_font_weight": "400",
                                        "typography_line_height": {
                                            "unit": "px",
                                            "size": 26,
                                            "sizes": []
                                        },
                                        "text_color": "#BABBC3"
                                    },
                                    "widgetType": "text-editor",
                                    "elType": "widget"
                                }
                            ],
                            "elType": "container",
                            "isInner": true
                        }
                    ],
                    "elType": "container",
                    "isInner": true
                }
            ],
            "elType": "container",
            "isInner": false
        }
    ]
}